{
    "absolute": {
        "cfg_build_number" : {
            "name": "Build number",
            "mode": "readonly",
            "desc": "Build comaptibile with this config"
        },
        "cfg_gui_contrast" : {
            "name": "LCD contrast",
            "desc": "",
            "mode": "slider",
            "min": 0,
            "max": 10,
            "step": 1
        },
        "cfg_gui_brightness" : {
            "name": "Backlight",
            "desc": "in %",
            "mode": "slider",
            "min": 0,
            "max": 100,
            "step": 10
        },    
        "cfg_gui_brightness_timeout" : {
            "name": "Backlight timeout",
            "desc": "in seconds",
            "mode": "slider",
            "min": 0,
            "max": 30,
            "step": 1
        }, 
        "cfg_gui_disp_flags" : {
            "name": "Display configuration",
            "mode": "flags",
            "flags": [
                ["CFG_DISP_INVERT", "Invert display"],
                ["CFG_DISP_FLIP", "Flip display"],
                ["CFG_DISP_ANIM", "Enable animations"]
            ]
        },
        "cfg_gui_menu_audio_flags" : {
            "name": "Menu sound configuration",
            "mode": "flags",
            "flags": [
                ["CFG_AUDIO_MENU_SPLASH", "On/Off sound"],
                ["CFG_AUDIO_MENU_PAGES", "Page sound"],
                ["CFG_AUDIO_MENU_BUTTONS", "Button sound"]
            ]
        },        
        "cfg_gui_last_page" : {
        	"name": "Page active in last shutdown",
            "mode": "readonly"
        },
        "cfg_gui_menu_volume" : {
            "name": "Menu sound volume",
            "desc": "in %",
            "mode": "slider",
            "min": 0,
            "max": 100,
            "step": 10
        },       
        "cfg_gui_vario_volume" : {
            "name": "Vario volume",
            "desc": "in %",
            "mode": "slider",
            "min": 0,
            "max": 100,
            "step": 10
        },   
        "cfg_gui_alert_volume" : {
            "name": "Alert volume",
            "desc": "in %",
            "mode": "slider",
            "min": 0,
            "max": 100,
            "step": 10
        },
        "cfg_vario_weak_lift_enabled" : {
            "name": "Weak lift",
            "desc": "Enable week lift",
            "mode": "bool"
        },     
        "cfg_gui_vario_mute" : {
            "name": "Mute vario",
            "desc": "Disable audio vario",
            "mode": "bool"
        },
        "cfg_gui_number_of_pages" : {
            "name": "Number of pages",
            "desc": "",
            "mode": "number",
            "min": 1,
            "max": 5
        },
        "cfg_vario_flags" : {
            "name": "Vario Flags",
            "mode": "flags",
            "flags": [
                ["VARIO_UNITS_I", "Use imperial units"]
            ]
        },    
        "cfg_vario_weak_lift" : {
            "name": "Weak lift treshold",
            "desc": "in cm/s",
            "mode": "number",
            "min": 10,
            "max": 200,
            "step": 10
        },              
        "cfg_audio_profile_weak_lift_freq" : {
            "name": "Weak lift buzzer frequency",
            "desc": "in Hz",
            "mode": "number",
            "min": 10,
            "max": 2000,
            "step": 10
        },
        "cfg_altitude_alt1_flags" :
        {
            "name": "Altimeter 1 flags",
            "mode": "flags",
            "flags": [
                ["ALT_UNIT_I", "Use imperial units"]
            ]
        },
        "cfg_audio_profile_fluid" : {
            "name": "Fluid Audio",
            "desc": "Enable fluent frequency change",
            "mode": "bool"
        },
        "cfg_audio_profile_lift" : {
            "name": "Lift treshold",
            "desc": "in cm/s",
            "mode": "number",
            "min": -2000,
            "max": 2000,
            "step": 10
        },
        "cfg_audio_profile_sink" : {
            "name": "Sink treshold",
            "desc": "in cm/s",
            "mode": "number",
            "min": -2000,
            "max": 2000,
            "step": 10
        },
        "cfg_connectivity_use_gps" : {
            "name": "Enable GPS",
            "desc": "",
            "mode": "bool"
        },
        "cfg_connectivity_use_bt" : {
            "name": "Enable Bluetooth",
            "desc": "",
            "mode": "bool"
        },
        "cfg_connectivity_forward_gps" : {
            "name": "Send GPS via Bluetooth",
            "desc": "",
            "mode": "bool"
        },
        "cfg_system_debug_log" : {
            "name": "Enable system logging",
            "desc": "",
            "mode": "bool"
        },
        "cfg_system_debug_gps" : {
            "name": "Enable GPS debuging",
            "desc": "Will output GPS data to the debug stream",
            "mode": "bool"
        },        
        "cfg_connectivity_usb_mode" : {
            "name": "Enable USB mode",
            "desc": "Go to USB mode even when in active mode",
            "mode": "bool"
        },
        "cfg_autostart_flags" : {
            "name": "Auto start settings",
            "mode": "flags",
            "flags": [
                ["AUTOSTART_SUPRESS_AUDIO", "Supress audio before take-off"],
                ["AUTOSTART_ALWAYS_ENABLED", "Always start recording after power on"]
            ]            
        },
        "cfg_logger_format" : {
            "name": "Log file format",
            "mode": "select",
            "options": [
                ["LOGGER_IGC", "IGC"],
                ["LOGGER_KML", "KML"],
                ["LOGGER_RAW", "RAW"]
            ]
        },
        "cfg_connectivity_protocol" : {
            "name": "Remote communication protocol",
            "mode": "select",
            "options": [
                ["PROTOCOL_DIGIFLY", "DigiFly"],
                ["PROTOCOL_LK8EX1", "LK8EX1"],
                ["PROTOCOL_BLUEFLY", "BlueFly (pressure only)"],
                ["PROTOCOL_SKYBEAN", "SkyBean (in development)"]
            ]
        },
        "cfg_connectivity_gps_format_flags" : {
            "name": "GPS flags",
            "mode": "doubleselect",
            "label1" : "GPS coordinates format",
            "mask1" : "GPS_FORMAT_MASK",
            "options1": [
                ["GPS_DDdddddd", "DD.dddddd"],
                ["GPS_DDMMmmm", "DD°MM.mmm"],
                ["GPS_DDMMSS", "DD°MM'SS"]
            ],
            "label2" : "GPS speed units",
            "mask2" : "GPS_SPD_MASK",
            "options2": [
                ["GPS_SPD_MS", "m/s"],
                ["GPS_SPD_KPH", "Km/h"],
                ["GPS_SPD_MPH", "MPH"],
                ["GPS_SPD_KNOT", "Knots"]
            ]
        },
        "cfg_system_auto_power_off" : {
            "name": "Auto power-off",
            "desc": "in min",
            "mode": "number",
            "min": 0,
            "max": 120,
            "step": 1
        },
        "cfg_system_time_flags" : {
            "name": "Time flags",
            "mode": "flags",
            "flags": [
                ["TIME_DST", "Daylight saving time"],
                ["TIME_SYNC", "Sync time with GPS"]
            ]
        },
        "cfg_logger_enabled" : {
            "name": "Enable GPS logger",
            "desc": "",
            "mode": "bool"
        },      
        "cfg_autostart_land_sensititvity" : {
            "name": "Auto landing treshold",
            "desc": "in m / timeout",
            "mode": "number",
            "min": 0,
            "max": 100,
            "step": 1
        },            
        "cfg_autostart_start_sensititvity" : {
            "name": "Auto Take-off treshold",
            "desc": "in m / timeout",
            "mode": "number",
            "min": 0,
            "max": 100,
            "step": 1
        },            
        "cfg_autostart_timeout" : {
            "name": "Auto Take-off/Auto Land timeout",
            "desc": "in s",
            "mode": "number",
            "min": 5,
            "max": 240,
            "step": 1
        },
        "cfg_vario_digital_vario_dampening" : {
            "name": "Digital vario averaging",
            "desc": "in s",
            "mode": "dampening",
            "min": 0,
            "max": 30,
            "step": 0.1
        },
        "cfg_vario_avg_vario_dampening" : {
            "name": "Average vario averaging",
            "desc": "in s",
            "mode": "dampening",
            "min": 0,
            "max": 90,
            "step": 0.1
        },          
        "cfg_system_time_zone" : {
            "name": "Curent time zone",
            "desc": "from GTM",
            "mode": "select",
            "options": [
				[-24,"GTM - 12"],
				[-23,"GTM - 11,5"],
				[-22,"GTM - 11"],
				[-21,"GTM - 10,5"],
				[-20,"GTM - 10"],
				[-19,"GTM - 9,5"],
				[-18,"GTM - 9"],
				[-17,"GTM - 8,5"],
				[-16,"GTM - 8"],
				[-15,"GTM - 7,5"],
				[-14,"GTM - 7"],
				[-13,"GTM - 6,5"],
				[-12,"GTM - 6"],
				[-11,"GTM - 5,5"],
				[-10,"GTM - 5"],
				[-9,"GTM - 4,5"],
				[-8,"GTM - 4"],
				[-7,"GTM - 3,5"],
				[-6,"GTM - 3"],
				[-5,"GTM - 2,5"],
				[-4,"GTM - 2"],
				[-3,"GTM - 1,5"],
				[-2,"GTM - 1"],
				[-1,"GTM - 0,5"],
				[0,"GTM + 0"],
				[1,"GTM + 0,5"],
				[2,"GTM + 1"],
				[3,"GTM + 1,5"],
				[4,"GTM + 2"],
				[5,"GTM + 2,5"],
				[6,"GTM + 3"],
				[7,"GTM + 3,5"],
				[8,"GTM + 4"],
				[9,"GTM + 4,5"],
				[10,"GTM + 5"],
				[11,"GTM + 5,5"],
				[12,"GTM + 6"],
				[13,"GTM + 6,5"],
				[14,"GTM + 7"],
				[15,"GTM + 7,5"],
				[16,"GTM + 8"],
				[17,"GTM + 8,5"],
				[18,"GTM + 9"],
				[19,"GTM + 9,5"],
				[20,"GTM + 10"],
				[21,"GTM + 10,5"],
				[22,"GTM + 11"],
				[23,"GTM + 11,5"],
				[24,"GTM + 12"]
            ]
        },
        "cfg_logger_pilot" : {
            "name": "Pilot name",
            "desc": "for IGC record",
            "mode": "text",
            "size": 50
        },
        "cfg_logger_glider_type" : {
            "name": "Glider type",
            "desc": "for IGC record",
            "mode": "text",
            "size": 50
        },
        "cfg_logger_glider_id" : {
            "name": "Glider ID",
            "desc": "for IGC record",
            "mode": "text",
            "size": 50
        },
        "cfg_connectivity_uart_function" : {
            "name": "HW uart function",
            "mode": "select",
            "options": [
                ["UART_FORWARD_DEBUG", "Debug messages @ 921600"],
                ["UART_FORWARD_OFF", "Uart output off"],
                ["UART_FORWARD_9600", "Telemetry @ 9600"],
                ["UART_FORWARD_19200", "Telemetry @ 19200"],
                ["UART_FORWARD_38400", "Telemetry @ 38400"],
                ["UART_FORWARD_57600", "Telemetry @ 57600"],
                ["UART_FORWARD_115200", "Telemetry @ 115200"]
            ]
        },
        "cfg_gui_silent" : {
            "name": "Disable vario sound on specific screens",
            "mode": "flags",
            "flags": [
                [1, "Screen 1"],
                [2, "Screen 2"],
                [4, "Screen 3"],
                [8, "Screen 4"],
                [16, "Screen 5"]
            ]
        },         
        "cfg_gui_hide_label" : {
            "name": "Disable widgets labels on specific screens",
            "mode": "flags",
            "flags": [
                [1, "Screen 1"],
                [2, "Screen 2"],
                [4, "Screen 3"],
                [8, "Screen 4"],
                [16, "Screen 5"]
            ]
        },
         "cfg_system_record_screen" : {
            "name": "Record screen",
            "desc": "Do NOT enable, for debug and testing only!",
            "mode": "bool"
        },
        "cfg_connectivity_password" : {
            "name": "connectivity password",
            "desc": "special case only, not used in drop",
            "mode": "text",
            "size": 16
        },
        "cfg_connectivity_bt_link_key" : {
            "name": "Bluetooth partner pair key",
            "mode": "readonly",
            "size": 16
        },    
        "cfg_connectivity_bt_link_partner" : {
            "name": "Bluetooth partner MAC address",
            "mode": "readonly",
            "size": 6
        },               
        "cfg_connectivity_btle_mac" : {
            "name": "Bluetooth Low energy random MAC address",
            "mode": "readonly",
            "size": 6
        }            
    },
    
    "regexp": {
        "cfg_gui_pages_[0-4]_type" : {
            "name": "Page layout type",
            "mode": "select",
            "options": [
                ["LAYOUT_1", "Layout 1"],
                ["LAYOUT_113", "Layout 1 | 1 | 3"],
                ["LAYOUT_12", "Layout 1 | 2"],
                ["LAYOUT_121", "Layout 1 | 2 | 1"],
                ["LAYOUT_122", "Layout 1 | 2 | 2"],
                ["LAYOUT_123", "Layout 1 | 2 | 3"],
                ["LAYOUT_21", "Layout 2 | 1"],
                ["LAYOUT_22", "Layout 2 | 2"],
                ["LAYOUT_222", "Layout 2 | 2 | 2"],
                ["LAYOUT_333", "Layout 3 | 3 | 3"]
            ]
        },
        "cfg_gui_pages_[0-4]_widgets_[0-8]" : {
            "name": "Widget type",
            "mode": "select",
            "options": [
                ["WIDGET_EMPTY", "No widget"],
                ["WIDGET_DEBUG_ETC", "Debug info"],
                ["WIDGET_DEBUG_IMU", "Debug info IMU"],
                ["WIDGET_VARIO", "Digital vario"],
                ["WIDGET_AVG_VARIO", "Average vario"],
                ["WIDGET_VARIO_BAR", "Analog vario bar"],
                ["WIDGET_VARIO_HISTORY", "Vario history"],
                ["WIDGET_ALT1", "Altitude 1"],
                ["WIDGET_ALT2", "Altitude 2"],
                ["WIDGET_ALT3", "Altitude 3"],
                ["WIDGET_ALT4", "Altitude 4"],
                ["WIDGET_ALT5", "Altitude 5"],
                ["WIDGET_ACC_TOT", "Total acceleration"],
                ["WIDGET_TIME", "Actual time"],
                ["WIDGET_DATE", "Actual date"],
                ["WIDGET_FTIME", "Flight time"],
                ["WIDGET_TEMPERATURE", "Temperature and humidity"],
                ["WIDGET_GHEADING", "GPS heading"],
                ["WIDGET_GROUND_SPD", "Ground speed"],
                ["WIDGET_POSITION", "GPS position"],
                ["WIDGET_GHEADING_ARROW", "GPS Heading arrow"],
                ["WIDGET_BATTERY", "Battery status"],
                ["WIDGET_GLIDE_RATIO", "Glide ratio"],
                ["WIDGET_CTRL_AUDIO", "Enable/Disable audio vario"],
                ["WIDGET_CTRL_WLIFT", "Enable/Disable weaklift"],
                ["WIDGET_WIND_DIR", "Wind direction"],
                ["WIDGET_WIND_DIR_ARROW", "Wind direction arrow"],
                ["WIDGET_WIND_SPD", "Wind speed"],
                ["WIDGET_GCOMPASS", "GPS compass"],
                ["WIDGET_AGL_HEIGHT", "Altitude abore ground"],
                ["WIDGET_AGL_LEVEL", "Ground level"],
                ["WIDGET_ODO_METER", "Odometer"],
                ["WIDGET_ODO_BACK", "Back"],
                ["WIDGET_ODO_DISTANCE", "Distance"]
            ]
        },
        "cfg_audio_profile_freq_[0-9]" : {
            "name": "Buzzer frequency",
            "desc": "in Hz",
            "mode": "number",
            "min": 0,
            "max": 2000,
            "link": "audio_profile"            
        },
        "cfg_audio_profile_pause_[0-9]" : {
            "name": "Pause before next beep",
            "desc": "in ms",
            "mode": "number",
            "min": 0,
            "max": 2000,            
            "link": "audio_profile"
        },
        "cfg_audio_profile_length_[0-9]" : {
            "name": "Beep duration",
            "desc": "in ms",
            "mode": "number",
            "min": 0,
            "max": 2000,
            "link": "audio_profile"           
        },
        "cfg_altitude_altimeter_[0-3]_flags" :
        {
           "name": "Altimeter flags",
            "mode": "altimeter",
            "options_mask": "ALT_MODE_MASK",
            "options": [
                ["ALT_ABS_QNH1", "Absolute to QNH1"],
                ["ALT_ABS_QNH2", "Absolute to QNH2"],
                ["ALT_ABS_GPS", "Absolute to GPS"],
                ["ALT_DIFF", "Relative"]
            ],            
            "flags": [
                ["ALT_AUTO_ZERO", "Zero at Take-off"],
                ["ALT_UNIT_I", "Use imperial units"]
            ],
            "altimeters_mask": "ALT_REL_MASK",
            "altimeters": [
                [0, "Altimeter 1"],
                [1, "Altimeter 2"],
                [2, "Altimeter 3"],
                [3, "Altimeter 4"],
                [4, "Altimeter 5"]
            ]
        },
        "cfg_altitude_altimeter_[0-3]_delta" : {
            "name": "Altimeter delta",
            "desc": "in meters",
            "mode": "number",
            "min": -32000,
            "max": 32000
        },
        "cfg_altitude_QNH[1-2]" :
        {
            "name": "Barometric pressure adjusted to sea level",
            "desc": "in Pa",
            "mode": "number",
            "min" : 80000,
            "max" : 1050000,
            "step": 1
        }
    },
    "widgets" :
    {
        "WIDGET_EMPTY": 
        {
        	"type": "empty",
			"name": "No widget",
			"desc": "Empty space"
        },
        "WIDGET_VARIO": 
        {
        	"type": "value",
			"name": "Digital vario",
			"desc": "Actual lift/sink value in m/s or ft/m", 
			"label": "Vario", 
			"value": "1.8"
        },
        "WIDGET_AVG_VARIO": 
        {
        	"type": "value",
			"name": "Average vario",
			"desc": "Average lift/sink in m/s or ft/m", 
			"label": "Avg", 
			"value": "1.2"
        },
        "WIDGET_VARIO_HISTORY": 
        {
        	"type": "graph",
			"name": "Vario graph history",
			"desc": "Vario value ploted over averaging interval"
        },
        "WIDGET_VARIO_BAR": 
        {
        	"type": "bar",
			"name": "Vario bar",
			"desc": "Graphical representation of actual Vario value"
        },
        "WIDGET_GHEADING_ARROW": 
        {
        	"type": "arrow",
			"name": "GPS heading arrow",
			"desc": "Arrow showing actual GPS heading", 
			"label": "GHdg" 
        },
        "WIDGET_GHEADING":
        {
         	"type": "value",
			"name": "Ground heading",
			"desc": "Actual ground heading based on GPS (0 = N, 90 = E, 180 = S, 270 = W)", 
			"label": "GHdg", 
			"value": "75"
        },
        "WIDGET_GROUND_SPD":
        {
         	"type": "value",
			"name": "Ground speed",
			"desc": "Actual ground speed based on GPS in Km/h, MPH, knots or m/s", 
			"label": "GSpd", 
			"value": "35"
        },
        "WIDGET_ALT1":
        {
         	"type": "value",
			"name": "Altitude 1",
			"desc": "Absolute altitude based on QNH1", 
			"label": "Alt1", 
			"value": "587"
        },
        "WIDGET_ALT2":
        {
         	"type": "value",
			"name": "Altitude 2",
			"desc": "User defined absolute, relative or GPS altitude", 
			"label": "Alt2", 
			"value": "251"
        },
        "WIDGET_ALT3":
        {
         	"type": "value",
			"name": "Altitude 3",
			"desc": "User defined absolute, relative or GPS altitude", 
			"label": "Alt3", 
			"value": "42"
        },
        "WIDGET_ALT4":
        {
         	"type": "value",
			"name": "Altitude 4",
			"desc": "User defined absolute, relative or GPS altitude", 
			"label": "Alt4", 
			"value": "125"
        },
        "WIDGET_ALT5":
        {
         	"type": "value",
			"name": "Altitude 5",
			"desc": "User defined absolute, relative or GPS altitude", 
			"label": "Alt5", 
			"value": "785"
        },
        "WIDGET_TIME":
        {
         	"type": "value",
			"name": "Time",
			"desc": "Actual time from real time clock", 
			"label": "Time", 
			"value": "13:24"
        },
        "WIDGET_DATE":
        {
         	"type": "value",
			"name": "date",
			"desc": "Actual date from real time clock", 
			"label": "Date", 
			"value": "13/11"
        },
        "WIDGET_FTIME":
        {
         	"type": "value",
			"name": "Flight time",
			"desc": "Showing flight duration time, can be used as flight start/stop", 
			"label": "FTime", 
			"value": "56.21"
        },
        "WIDGET_TEMPERATURE":
        {
         	"type": "temperature",
			"name": "Temperature and humidity",
			"desc": "Showing actual temperature in °C and relative humidity in %", 
			"label": "Temp", 
			"value1": "28.2",
			"value2": "62%"
        },        
        "WIDGET_GLIDE_RATIO":
        {
         	"type": "value",
			"name": "Glide ratio",
			"desc": "Ratio between horizontal a vertical speed", 
			"label": "Glide", 
			"value": "10.1"
        },
        "WIDGET_BATTERY":
        {
         	"type": "text",
			"name": "Battery level",
			"desc": "Battery level and charging indicator", 
			"label": "Bat", 
			"value": "100%"
        },    
        "WIDGET_POSITION":
        {
         	"type": "text2",
			"name": "GPS position",
			"desc": "Actual GPS possition in DD.dddddd, DD°MM.mmm or DD°MM'SS", 
			"label": "GPos", 
			"value": "48.46357150 17.42317721"
        },
        "WIDGET_CTRL_AUDIO":
        {
         	"type": "text",
			"name": "Vario mute control",
			"desc": "Indication and control widget for audio vario", 
			"label": "", 
			"value": "beep"
        },
        "WIDGET_CTRL_WLIFT":
        {
         	"type": "text",
			"name": "Weaklift control",
			"desc": "Indication and control widget for weaklift detection", 
			"label": "", 
			"value": "weak"
        },
        "WIDGET_WIND_DIR_ARROW": 
        {
            "type": "arrow",
            "name": "Wind direction arrow",
            "desc": "Arrow showing actual wind direction, relative to GPS heading", 
            "label": "WDir" 
        },
        "WIDGET_GCOMPASS": 
        {
            "type": "arrow",
            "name": "GPS compass arrow",
            "desc": "Arrow showing north based on GPS, relative to GPS heading", 
            "label": "GCom" 
        },
        "WIDGET_WIND_DIR":
        {
            "type": "value",
            "name": "Wind direction",
            "desc": "Absolute direction of wind source (0 = N, 90 = E, 180 = S, 270 = W)", 
            "label": "WDir", 
            "value": "20"
        },
        "WIDGET_WIND_SPD":
        {
            "type": "value",
            "name": "Wind speed",
            "desc": "Calculated wind speed", 
            "label": "WSpd", 
            "value": "5"
        },      
        "WIDGET_AGL_HEIGHT":
        {
            "type": "value",
            "name": "Height above ground level",
            "desc": "Calculated distance between you and the terrain", 
            "label": "HAGL", 
            "value": "437"
        },       
        "WIDGET_AGL_LEVEL":
        {
            "type": "value",
            "name": "Ground level",
            "desc": "Terrain height above see estimated from GPS position and altitude data file", 
            "label": "GLevel", 
            "value": "150"
        },    
        "WIDGET_ACC_TOT":
        {
            "type": "value",
            "name": "Total acceleration",
            "desc": "Total acceleration in g", 
            "label": "Acc", 
            "value": "1.0"
        },
        "WIDGET_ODO_METER":
        {
            "type": "value",
            "name": "Odometer",
            "desc": "Flown distance",
            "label": "Odo",
            "value": "13.8"
        },
        "WIDGET_ODO_BACK":
        {
            "type": "arrow",
            "name": "Arrow to home",
            "desc": "Arrow showing direction to take-off position",
            "label": "Home"
        },
        "WIDGET_ODO_DISTANCE":
        {
            "type": "value",
            "name": "Distance from home",
            "desc": "Direct distance measured from take-off position",
            "label": "Home",
            "value": "8.1"
        }
    }
}            
