<?xml version="1.0" encoding="UTF-8" standalone="yes"?>
<OPENAIP VERSION="1708909912012" DATAFORMAT="1.1">
 <AIRSPACES><ASP CATEGORY="C"><VERSION>1708909912012</VERSION><ID>62614fedcb27f4250946088c</ID><COUNTRY>QA</COUNTRY><NAME>DOHA TMA 1</NAME><ALTLIMIT_TOP REFERENCE="MSL"><ALT UNIT="F">4500</ALT></ALTLIMIT_TOP><ALTLIMIT_BOTTOM REFERENCE="MSL"><ALT UNIT="F">2500</ALT></ALTLIMIT_BOTTOM><GEOMETRY><POLYGON>51.738333333333 25.922777777778,51.935555555556 25.618055555556,51.955833333333 25.1375,51.923333333333 24.8775,51.791111111111 24.820555555556,51.487777777778 24.811944444444,51.297222222222 25.283888888889,51.294444444444 25.496111111111,51.492777777778 25.793055555556,51.58 25.868888888889,51.738333333333 25.922777777778</POLYGON></GEOMETRY></ASP><ASP CATEGORY="CTR"><VERSION>1708909912012</VERSION><ID>62614fed0e8346dfd924ff7d</ID><COUNTRY>QA</COUNTRY><NAME>DOHA CTR 118.900</NAME><ALTLIMIT_TOP REFERENCE="MSL"><ALT UNIT="F">2500</ALT></ALTLIMIT_TOP><ALTLIMIT_BOTTOM REFERENCE="GND"><ALT UNIT="F">0</ALT></ALTLIMIT_BOTTOM><GEOMETRY><POLYGON>51.62777777777778 25.56861111111111,51.655277777777776 25.50638888888889,51.655277777777776 25.50638888888889,51.66690192559783 25.50589978261552,51.67850317350854 25.50508047139714,51.69006997800295 25.50393177054247,51.7015908307053 25.50245482311198,51.713054270103726 25.50065109875171,51.72444889323054 25.498522392193976,51.73576336727683 25.496070821426844,51.74698644112876 25.493298825534335,51.758106956812426 25.490209162209727,51.76911386083481 25.486804904944886,51.779996215408076 25.483089439898617,51.79074320954515 25.479066462447616,51.801344170014055 25.474739973423905,51.80972222222222 25.470555555555553,51.80972222222222 25.470555555555553,51.92166666666667 25.21527777777778,51.92166666666667 25.21527777777778,51.91758615277665 25.20550674977314,51.913169120403786 25.195856378475938,51.90841999404581 25.186336157555342,51.903343521610765 25.1769554504535,51.897944769497066 25.16772348127152,51.89222911737745 25.1586493257993,51.886202252692726 25.149741902697404,51.879870164861416 25.14100996483924,51.87323913921171 25.13246209082152,51.86631575064221 25.124106676650708,51.859106857018304 25.115951927613164,51.851619592311 25.108005850336312,51.84386135948525 25.100276245048132,51.835839823145115 25.09277069804192,51.82756290194323 25.085496574353176,51.819038760761835 25.078461010655154,51.810275802673345 25.071670908379534,51.80128266068823 25.065132927068323,51.792068189297915 25.058853477962963,51.78264145582118 25.052838717836234,51.77301173156178 25.04709454307271,51.763188482785985 25.04162658400265,51.75318136152817 25.036440199494663,51.743000196232934 25.03154047181171,51.73265498224252 25.026932201735054,51.722155872138 25.02261990396048,51.71151316594297 25.01860780277071,51.70073730119868 25.014899827987936,51.689838842919336 25.01149961120988,51.67882847343655 25.008410482332838,51.66771698214192 25.005635466364488,51.6565152551368 25.003177280529535,51.645234264798255 25.001038331670454,51.63388505927041 24.99922071394573,51.622478751890355 24.99772620682757,51.61102651055765 24.996556273400785,51.599539547056835 24.995712058964347,51.58802910634206 24.99519438993685,51.57650645579316 24.99500377306674,51.564982874452305 24.995140394948123,51.55346964225071 24.99560412184246,51.54197802923456 24.99639449980637,51.530519284799375 24.997510755125358,51.51910462694228 24.998951795053213,51.50774523154124 25.000716208856293,51.49645222167069 25.002802269161926,51.485236656962655 25.005207933609643,51.47410952302275 25.007930846803905,51.463081720910004 25.010968342566578,51.45216405669001 25.014317446487212,51.44136723107011 25.017974878768932,51.43070182912611 25.021937057367403,51.42017831012927 25.026200101420276,51.410555555555554 25.02861111111111,51.410555555555554 25.02861111111111,51.325 24.997500000000002,51.308611111111105 25.034722222222225,51.308611111111105 25.034722222222225,51.305714552592725 25.03488195256602,51.30282495039581 25.03512398338501,51.299945150445524 25.03544807631025,51.297077989071944 25.035853912150092,51.29422629023323 25.036341091202623,51.2913928627507 25.036909133646954,51.28858049755824 25.037557480012964,51.285791964969015 25.038285491729027,51.28303001196158 25.039092451747248,51.280297359488664 25.039977565245554,51.27759669981045 25.040939960406007,51.274930693855666 25.041978689268575,51.27230196861235 25.043092728659587,51.26971311455124 25.0442809811939,51.26716668308422 25.045542276349885,51.26466518405995 25.046875371616196,51.26221108329954 25.048278953709218,51.2598068001743 25.049751639859995,51.2574547052282 25.051291979169417,51.25515711784698 25.052898454030455,51.252916303976626 25.05456948161589,51.25073447389309 25.056303415430317,51.24861378002549 25.05809854692474,51.246556314835104 25.059953107172415,51.244564108752 25.061865268604063,51.242639128171554 25.063833146801056,51.2407832735125 25.06585480234463,51.23899837733897 25.067928242719503,51.237286202547786 25.07005142426992,51.23564844062319 25.07222225420636,51.2340867099607 25.07443859266083,51.23260255426165 25.076698254788948,51.23119744100022 25.078999012916544,51.22987275996417 25.081338598728916,51.228629821871216 25.083714705500448,51.227469857062154 25.08612499036254,51.226394014272074 25.08856707660758,51.225403359481064 25.09103855602676,51.22449887484556 25.093536991279414,51.22368145771139 25.096059918291598,51.222951919709665 25.0986048486816,51.22231098593634 25.101169272209905,51.221759294216504 25.103750659251375,51.221297394454076 25.106346463287093,51.22092574806764 25.108954123413472,51.22064472751311 25.111571066866244,51.22045461589383 25.11419471155666,51.22035560665834 25.11682246861771,51.220347803386574 25.11945174495748,51.22043121966442 25.122079945817518,51.220605779047126 25.124704477333378,51.220871315111516 25.127322749095008,51.22122757159716 25.12993217670435,51.22167420263635 25.13253018432771,51.22221077307288 25.13511420724025,51.222836758869235 25.137681694360246,51.22355154760208 25.140230110770425,51.224354439045406 25.142756940224007,51.225244645841066 25.1452596876329,51.226221294255964 25.14773588153561,51.22728342502539 25.15018307654237,51.22842999428143 25.15259885575505,51.22965987456612 25.154980833159506,51.23097185592782 25.15732665598787,51.23236464710029 25.159634007048524,51.23383687676307 25.161900607021334,51.23538709488207 25.16412421671594,51.2370137741291 25.16630263929074,51.23871531137901 25.168433722430418,51.24049002928291 25.17051536047981,51.24233617791609 25.172545496531928,51.24425193649887 25.174522124468094,51.24611111111111 25.175555555555558,51.24611111111111 25.175555555555558,51.21194444444445 25.252777777777776,51.2975 25.284166666666668,51.2975 25.284166666666668,51.30154614469118 25.293958583319494,51.30593114767654 25.3036306332743,51.31065074894136 25.3131732418318,51.315700354048 25.322576960164632,51.32107503841375 25.331832474765356,51.32676955193183 25.34093061676805,51.33277832393216 25.34986237113378,51.33909546847779 25.35861888569048,51.34571478999286 25.367191480017492,51.35262978921713 25.37557165416574,51.35983366948179 25.383751097203994,51.36731934330133 25.391721695582465,51.375079439275154 25.39947554130458,51.38166666666667 25.406666666666666,51.38166666666667 25.406666666666666,51.35416666666667 25.468888888888888,51.35416666666667 25.468888888888888,51.36244542817481 25.476223651989464,51.37097630615957 25.483319550169128,51.37975087455574 25.490169537840313,51.38876046083107 25.496766812378873,51.39799615459272 25.50310482100769,51.40744881645239 25.509177267432026,51.41710908714124 25.514978118219506,51.42696739686516 25.52050160891761,51.437013974890675 25.52574224990208,51.44723885935168 25.5306948319498,51.4576319072664 25.535354431529896,51.46818280475416 25.53971641580744,51.47888107744099 25.543776447353935,51.489716101042966 25.547530488559648,51.50067711211567 25.550974805742676,51.51175321895829 25.554105972950286,51.52293341266038 25.55692087544824,51.53420657827909 25.559416712894276,51.54556150613474 25.5615910021921,51.556986903212064 25.56344158002281,51.56847140465461 25.56496660505084,51.58000358533951 25.566164559801948,51.59157197151964 25.567034252211197,51.60316505252029 25.567574816839173,51.61477129247716 25.567785715755004,51.62637914210259 25.567666739085315,51.62777777777778 25.56861111111111,51.62777777777778 25.56861111111111</POLYGON></GEOMETRY></ASP><ASP CATEGORY="C"><VERSION>1708909912012</VERSION><ID>62614fed0e8346dfd924ff87</ID><COUNTRY>QA</COUNTRY><NAME>DOHA TMA 1A</NAME><ALTLIMIT_TOP REFERENCE="MSL"><ALT UNIT="F">4500</ALT></ALTLIMIT_TOP><ALTLIMIT_BOTTOM REFERENCE="MSL"><ALT UNIT="F">2500</ALT></ALTLIMIT_BOTTOM><GEOMETRY><POLYGON>51.160277777778 25.47,51.294444444444 25.496111111111,51.297222222222 25.283888888889,51.487777777778 24.811944444444,51.791111111111 24.820555555556,51.661111111111 24.665,51.438888888889 24.708888888889,51.3025 24.911944444444,51.163333333333 25.241388888889,51.160277777778 25.47</POLYGON></GEOMETRY></ASP><ASP CATEGORY="C"><VERSION>1708909912012</VERSION><ID>62614fedcb27f42509460896</ID><COUNTRY>QA</COUNTRY><NAME>DOHA TMA 2</NAME><ALTLIMIT_TOP REFERENCE="MSL"><ALT UNIT="F">4500</ALT></ALTLIMIT_TOP><ALTLIMIT_BOTTOM REFERENCE="MSL"><ALT UNIT="F">3500</ALT></ALTLIMIT_BOTTOM><GEOMETRY><POLYGON>51.738333333333 25.922777777778,51.803333333333 25.944722222222,52.005277777778 25.849166666667,52.204722222222 25.353888888889,52.137777777778 24.911388888889,52.021666666667 24.912222222222,51.923333333333 24.8775,51.955833333333 25.1375,51.935555555556 25.618055555556,51.738333333333 25.922777777778</POLYGON></GEOMETRY></ASP><ASP CATEGORY="C"><VERSION>1708909912012</VERSION><ID>62614fed0e8346dfd924ff9b</ID><COUNTRY>QA</COUNTRY><NAME>DOHA TMA 2A</NAME><ALTLIMIT_TOP REFERENCE="MSL"><ALT UNIT="F">4500</ALT></ALTLIMIT_TOP><ALTLIMIT_BOTTOM REFERENCE="MSL"><ALT UNIT="F">3500</ALT></ALTLIMIT_BOTTOM><GEOMETRY><POLYGON>51.438797222222 24.709005555556,51.661202777778 24.665086111111,51.647586111111 24.648758333333,51.613152777778 24.503469444444,51.434447222222 24.538772222222,51.465252777778 24.669547222222,51.438797222222 24.709005555556</POLYGON></GEOMETRY></ASP><ASP CATEGORY="C"><VERSION>1708909912012</VERSION><ID>62614fedcb27f425094608a3</ID><COUNTRY>QA</COUNTRY><NAME>DOHA TMA 3</NAME><ALTLIMIT_TOP REFERENCE="STD"><ALT UNIT="FL">145</ALT></ALTLIMIT_TOP><ALTLIMIT_BOTTOM REFERENCE="MSL"><ALT UNIT="F">4500</ALT></ALTLIMIT_BOTTOM><GEOMETRY><POLYGON>52.827222222222 25.456111111111,52.334166666667 24.797222222222,51.701666666667 24.713611111111,51.6475 24.648611111111,51.613055555556 24.503333333333,51.583333333333 24.426666666667,50.984722222222 24.423055555556,50.816666666667 24.75,50.647777777778 25.262777777778,50.838333333333 25.665,51.078333333333 26.284166666667,52.827222222222 25.456111111111</POLYGON></GEOMETRY></ASP><ASP CATEGORY="DANGER"><VERSION>1708909912012</VERSION><ID>62614fedcb27f425094608b0</ID><COUNTRY>QA</COUNTRY><NAME>OT-D17</NAME><ALTLIMIT_TOP REFERENCE="MSL"><ALT UNIT="F">20000</ALT></ALTLIMIT_TOP><ALTLIMIT_BOTTOM REFERENCE="GND"><ALT UNIT="F">0</ALT></ALTLIMIT_BOTTOM><GEOMETRY><POLYGON>50.75 25.430555555556,50.766666666667 25.116666666667,50.861111111111 24.763888888889,50.816666666667 24.75,50.666666666667 25.116666666667,50.616666666667 25.416666666667,50.75 25.430555555556</POLYGON></GEOMETRY></ASP><ASP CATEGORY="DANGER"><VERSION>1708909912012</VERSION><ID>62614fedcb27f425094608ba</ID><COUNTRY>QA</COUNTRY><NAME>OT-D1 ALQALAEL</NAME><ALTLIMIT_TOP REFERENCE="MSL"><ALT UNIT="F">10000</ALT></ALTLIMIT_TOP><ALTLIMIT_BOTTOM REFERENCE="GND"><ALT UNIT="F">0</ALT></ALTLIMIT_BOTTOM><GEOMETRY><POLYGON>50.916666666667 24.6,50.916666666667 24.9,51.066666666667 24.9,51.066666666667 24.6,50.916666666667 24.6</POLYGON></GEOMETRY></ASP><ASP CATEGORY="DANGER"><VERSION>1708909912012</VERSION><ID>62614fedcb27f425094608c4</ID><COUNTRY>QA</COUNTRY><NAME>OT-D2</NAME><ALTLIMIT_TOP REFERENCE="MSL"><ALT UNIT="F">20000</ALT></ALTLIMIT_TOP><ALTLIMIT_BOTTOM REFERENCE="GND"><ALT UNIT="F">0</ALT></ALTLIMIT_BOTTOM><GEOMETRY><POLYGON>50.918611111111 24.601666666667,51.204722222222 24.598888888889,51.191111111111 24.497222222222,51.068888888889 24.496944444444,50.918611111111 24.601666666667</POLYGON></GEOMETRY></ASP><ASP CATEGORY="DANGER"><VERSION>1708909912012</VERSION><ID>62614feecb27f425094608cf</ID><COUNTRY>QA</COUNTRY><NAME>OT-D26 BIR ZIRKIT</NAME><ALTLIMIT_TOP REFERENCE="MSL"><ALT UNIT="F">3500</ALT></ALTLIMIT_TOP><ALTLIMIT_BOTTOM REFERENCE="GND"><ALT UNIT="F">0</ALT></ALTLIMIT_BOTTOM><GEOMETRY><POLYGON>50.866666666667 25.583277078909,50.87491449094 25.5829439064,50.883096228931 25.581947058458,50.891146327167 25.580294522321,50.899000293395 25.577999538477,50.90659521622 25.575080493942,50.913870271707 25.571560774065,50.920767212767 25.567468574104,50.927230837319 25.562836672128,50.933209431409 25.557702165096,50.938655183692 25.552106170299,50.943524567925 25.546093494612,50.947778690409 25.53971227425,50.951383599629 25.533013587997,50.954310555648 25.526051047032,50.956536257185 25.518880364712,50.958043024632 25.511558909785,50.958818937671 25.504145246658,50.958857926498 25.496698666413,50.958159816058 25.489278712367,50.956730323085 25.481944703947,50.954581006098 25.474755262727,50.951729168891 25.467767844362,50.948197718429 25.461038280181,50.944014978392 25.454620332035,50.939214459965 25.448565263947,50.933834591799 25.442921433926,50.927918411359 25.437733909153,50.921513220179 25.433044107562,50.91467020578 25.428889468624,50.907444033299 25.425303155889,50.899892410033 25.422313793624,50.892075626345 25.41994523958,50.88405607653 25.418216395659,50.875897763365 25.417141057954,50.867665790207 25.416727807309,50.859425844576 25.41697994127,50.851243677211 25.417895447931,50.843184580653 25.419467021889,50.835312871351 25.421682122183,50.827691379341 25.42452307177,50.820380949419 25.427967197756,50.813439957704 25.431987011321,50.806923847353 25.436550425916,50.80088468706 25.441621012046,50.795370755812 25.447158286677,50.790426157187 25.453118034976,50.786090466264 25.459452661909,50.782398411991 25.466111570925,50.779379597565 25.473041566769,50.777058261149 25.480187279251,50.7754530789 25.487491604641,50.774577011982 25.494896161202,50.774437198918 25.502341755243,50.775034894256 25.509768854009,50.776365454178 25.517118061624,50.778418369306 25.524330594294,50.781177344583 25.531348750958,50.784620425722 25.538116375603,50.788720171337 25.544579307528,50.793443869487 25.5506858159,50.798753796995 25.556387015093,50.804607519548 25.561637257433,50.810958230223 25.566394500141,50.817755123754 25.570620643489,50.824943803563 25.574281837393,50.832466718257 25.577348753935,50.84026362407 25.579796823566,50.848272069468 25.581606433058,50.856427897952 25.582763083565,50.864665764931 25.583257507497,50.866666666667 25.583277078909</POLYGON></GEOMETRY></ASP><ASP CATEGORY="DANGER"><VERSION>1708909912012</VERSION><ID>62614feecb27f425094608df</ID><COUNTRY>QA</COUNTRY><NAME>OT-D28 ALASHAT</NAME><ALTLIMIT_TOP REFERENCE="MSL"><ALT UNIT="F">10000</ALT></ALTLIMIT_TOP><ALTLIMIT_BOTTOM REFERENCE="GND"><ALT UNIT="F">0</ALT></ALTLIMIT_BOTTOM><GEOMETRY><POLYGON>52.266666666667 24.983333333333,52.266666666667 24.896666666667,52.24 24.875,51.833333333333 24.793333333333,51.833333333333 24.94,51.856666666667 24.956666666667,52.176666666667 25.008333333333,52.266666666667 24.983333333333</POLYGON></GEOMETRY></ASP><ASP CATEGORY="DANGER"><VERSION>1708909912012</VERSION><ID>62614feecb27f425094608eb</ID><COUNTRY>QA</COUNTRY><NAME>OT-D29</NAME><ALTLIMIT_TOP REFERENCE="MSL"><ALT UNIT="F">10000</ALT></ALTLIMIT_TOP><ALTLIMIT_BOTTOM REFERENCE="GND"><ALT UNIT="F">0</ALT></ALTLIMIT_BOTTOM><GEOMETRY><POLYGON>51.366666666667 25.141666666667,51.341666666667 25.175,51.366666666667 25.183333333333,51.391666666667 25.158333333333,51.366666666667 25.141666666667</POLYGON></GEOMETRY></ASP><ASP CATEGORY="PROHIBITED"><VERSION>1708909912012</VERSION><ID>62614feecb27f425094608f9</ID><COUNTRY>QA</COUNTRY><NAME>OT-P43</NAME><ALTLIMIT_TOP REFERENCE="MSL"><ALT UNIT="F">15000</ALT></ALTLIMIT_TOP><ALTLIMIT_BOTTOM REFERENCE="GND"><ALT UNIT="F">0</ALT></ALTLIMIT_BOTTOM><GEOMETRY><POLYGON>51 25.933333333333,51.333333333333 25.933333333333,51.333333333333 25.666666666667,51 25.666666666667,51 25.933333333333</POLYGON></GEOMETRY></ASP><ASP CATEGORY="PROHIBITED"><VERSION>1708909912012</VERSION><ID>62614feecb27f42509460906</ID><COUNTRY>QA</COUNTRY><NAME>OT-P44 WUSAYL</NAME><ALTLIMIT_TOP REFERENCE="MSL"><ALT UNIT="F">1500</ALT></ALTLIMIT_TOP><ALTLIMIT_BOTTOM REFERENCE="GND"><ALT UNIT="F">0</ALT></ALTLIMIT_BOTTOM><GEOMETRY><POLYGON>51.541666666667 25.466655415782,51.545331687017 25.466323370861,51.548850535895 25.465340479053,51.552082878494 25.463745940418,51.554899819189 25.461603346927,51.557189045296 25.458998143652,51.558859306229 25.45603421814,51.559844049208 25.452829754582,51.560104066935 25.44951251874,51.559629052562 25.446214762133,51.558438001235 25.443067948991,51.556578443696 25.440197516287,51.554124543921 25.437717875573,51.551174137822 25.435727855471,51.547844831794 25.434306765917,51.544269316802 25.433511240413,51.540590084402 25.433372981512,51.536953754404 25.433897498919,51.533505239001 25.435063890186,51.530381974539 25.436825672705,51.527708449474 25.439112634021,51.525591245556 25.441833627163,51.524114789271 25.444880200125,51.523337982834 25.448130915499,51.52329184955 25.451456188667,51.523978288413 25.454723452169,51.525369988961 25.457802440637,51.527411511257 25.460570385618,51.530021489349 25.462916912954,51.533095871413 25.464748446982,51.536512068004 25.46599194537,51.540133843027 25.466597815014,51.541666666667 25.466655415782</POLYGON></GEOMETRY></ASP><ASP CATEGORY="PROHIBITED"><VERSION>1708909912012</VERSION><ID>62614feecb27f42509460913</ID><COUNTRY>QA</COUNTRY><NAME>OT-P45 QATAR</NAME><ALTLIMIT_TOP REFERENCE="MSL"><ALT UNIT="F">1500</ALT></ALTLIMIT_TOP><ALTLIMIT_BOTTOM REFERENCE="GND"><ALT UNIT="F">0</ALT></ALTLIMIT_BOTTOM><GEOMETRY><POLYGON>51.528611111111 25.307766526893,51.532271311453 25.307434482297,51.535785532976 25.306451591412,51.53901362577 25.304857054152,51.541826863907 25.30271446227,51.5441130824 25.300109260586,51.545781150451 25.297145336395,51.546764602405 25.293940873679,51.547024282003 25.290623638067,51.546549895373 25.287325881042,51.54536041215 25.2841790669,51.543503300159 25.281308632772,51.541052625634 25.278828990435,51.53810609585 25.276838968767,51.534781162808 25.275417877951,51.531210343458 25.274622351688,51.5275359426 25.274484092651,51.523904387932 25.275008610567,51.520460401747 25.276175002907,51.517341240205 25.277936786893,51.514671228415 25.280223749841,51.512556808091 25.28294474452,51.511082294575 25.285991318682,51.510306512287 25.289242034729,51.510260443243 25.292567307938,51.51094598337 25.295834570842,51.512335857566 25.298913558166,51.514374698345 25.301681501641,51.516981246463 25.304028027343,51.520051586839 25.305859559869,51.523463291358 25.307103057124,51.527080303371 25.307708926181,51.528611111111 25.307766526893</POLYGON></GEOMETRY></ASP><ASP CATEGORY="PROHIBITED"><VERSION>1708909912012</VERSION><ID>62614feecb27f42509460920</ID><COUNTRY>QA</COUNTRY><NAME>OT-P46 RAYYAN</NAME><ALTLIMIT_TOP REFERENCE="MSL"><ALT UNIT="F">1500</ALT></ALTLIMIT_TOP><ALTLIMIT_BOTTOM REFERENCE="GND"><ALT UNIT="F">0</ALT></ALTLIMIT_BOTTOM><GEOMETRY><POLYGON>51.466666666667 25.299988749115,51.470326632112 25.299656704535,51.473840628127 25.298673813695,51.477068513812 25.297079276502,51.47988157151 25.294936684699,51.482167643431 25.292331483093,51.483835604615 25.289367558966,51.484818993654 25.286163096292,51.485078656773 25.282845860691,51.484604300736 25.279548103646,51.483414893932 25.276401289455,51.481557901122 25.273530855257,51.479107383775 25.271051212841,51.476161042898 25.269061191096,51.472836322967 25.267640100218,51.469265732452 25.266844573918,51.465591567053 25.266706314875,51.461960245103 25.267230832815,51.458516479643 25.268397225208,51.455397518052 25.270159009266,51.452727677476 25.272445972294,51.450613392807 25.275166967047,51.449138973969 25.278213541268,51.448363241592 25.281464257348,51.448317175678 25.284789530559,51.449002672008 25.288056793434,51.450392457199 25.291135780702,51.452431167298 25.293903724103,51.455037548261 25.296250249725,51.458107691671 25.298081782178,51.461519177274 25.299325279377,51.465135957169 25.299931148406,51.466666666667 25.299988749115</POLYGON></GEOMETRY></ASP><ASP CATEGORY="PROHIBITED"><VERSION>1708909912012</VERSION><ID>62614feecb27f4250946092d</ID><COUNTRY>QA</COUNTRY><NAME>OT-P47 QATAR</NAME><ALTLIMIT_TOP REFERENCE="MSL"><ALT UNIT="F">5000</ALT></ALTLIMIT_TOP><ALTLIMIT_BOTTOM REFERENCE="GND"><ALT UNIT="F">0</ALT></ALTLIMIT_BOTTOM><GEOMETRY><POLYGON>51.385555555556 25.321372012562,51.390050104801 25.321039391315,51.394424926749 25.32005038809,51.398563489175 25.318431347969,51.402355564139 25.316225397583,51.405700167805 25.313491294424,51.408508252074 25.31030185939,51.410705076003 25.306742034639,51.412232193823 25.302906618818,51.413049006807 25.298897740334,51.413133838104 25.29482213623,51.412484502571 25.290788309373,51.411118357201 25.286903639734,51.40907183161 25.283271526703,51.406399451889 25.279988638395,51.403172384453 25.277142340967,51.399476539149 25.274808376077,51.395410282345 25.273048847977,51.391081820874 25.271910573438,51.386606326186 25.271423838109,51.382102874762 25.271601592121,51.377691285544 25.272439106148,51.373488937795 25.273914097017,51.369607653287 25.275987319523,51.366150725069 25.278603608867,51.36321017132 25.281693346204,51.360864286992 25.28517430861,51.359175558284 25.288953854572,51.358188995582 25.292931387199,51.357930929624 25.2970010299,51.358408303512 25.30105444355,51.359608480172 25.304983710309,51.361499571199 25.308684207373,51.364031279121 25.312057394055,51.367136231397 25.315013437825,51.370731771132 25.317473609114,51.374722157179 25.319372380774,51.379001115078 25.320659175936,51.383454670712 25.321299717379,51.385555555556 25.321372012562</POLYGON></GEOMETRY></ASP><ASP CATEGORY="RESTRICTED"><VERSION>1708909912012</VERSION><ID>62614feecb27f4250946093a</ID><COUNTRY>QA</COUNTRY><NAME>OT-R51 AL GHARIYEH</NAME><ALTLIMIT_TOP REFERENCE="MSL"><ALT UNIT="F">3000</ALT></ALTLIMIT_TOP><ALTLIMIT_BOTTOM REFERENCE="GND"><ALT UNIT="F">0</ALT></ALTLIMIT_BOTTOM><GEOMETRY><POLYGON>51.344444444444 26.158554856687,51.35273252598 26.158221678188,51.360954195107 26.15722481247,51.369043574968 26.155572247336,51.376935855384 26.153277224206,51.384567815165 26.15035813135,51.39187833129 26.146838355661,51.39880887078 26.142746094184,51.405303961226 26.138114126953,51.411311636119 26.132979553013,51.416783851383 26.127383491795,51.421676869732 26.121370752294,51.425951609786 26.114989472765,51.429573957166 26.108290733879,51.432515035128 26.101328148497,51.434751432648 26.094157431392,51.436265388219 26.086835952422,51.437044928001 26.079422276758,51.437083957351 26.071975695882,51.436382305121 26.064555753127,51.434945720534 26.057221767559,51.432785822783 26.050032360019,51.429920003916 26.043044985088,51.426371285904 26.036315472705,51.422168133167 26.029897583069,51.417344222154 26.023842578336,51.411938169915 26.018198814494,51.405993223906 26.013011356612,51.399556915537 26.008321620493,51.392680680265 26.00416704352,51.385419447263 26.000580787269,51.377831201907 25.997591474207,51.36997652453 25.995222960516,51.361918109059 25.993494146814,51.353720265278 25.992418828229,51.345448408592 25.992005584998,51.337168541237 25.992257714431,51.328946728964 25.993173204766,51.320848577223 25.994744751119,51.312938710909 25.99695981341,51.305280261688 25.999800715804,51.297934366874 26.003244786913,51.290959683747 26.007264539666,51.284411923096 26.011827889449,51.278343405635 26.016898408837,51.272802644776 26.022435616921,51.267833959067 26.028395300991,51.263477117367 26.034729868061,51.259767019624 26.041388723492,51.256733415838 26.048318673737,51.254400665514 26.055464350064,51.252787539626 26.062768649899,51.25190706676 26.070173192319,51.251766424802 26.07761878409,51.252366879156 26.08504589253,51.253703768132 26.092395121458,51.255766535762 26.0996076864,51.258538811924 26.106625885265,51.261998539273 26.113393560697,51.26611814609 26.119856550373,51.270864763776 26.125963121615,51.276200487362 26.131664386791,51.282082677009 26.136914696118,51.288464298151 26.141672004675,51.29529429759 26.145898210631,51.302518012526 26.149559461901,51.310077609239 26.152626428731,51.317912547851 26.155074539965,51.325960069389 26.156884181044,51.334155701159 26.158040852113,51.34243377626 26.158535284922,51.344444444444 26.158554856687</POLYGON></GEOMETRY></ASP><ASP CATEGORY="RESTRICTED"><VERSION>1708909912012</VERSION><ID>62614feecb27f42509460947</ID><COUNTRY>QA</COUNTRY><NAME>OT-R53 QATAR</NAME><ALTLIMIT_TOP REFERENCE="MSL"><ALT UNIT="F">3000</ALT></ALTLIMIT_TOP><ALTLIMIT_BOTTOM REFERENCE="GND"><ALT UNIT="F">0</ALT></ALTLIMIT_BOTTOM><GEOMETRY><POLYGON>51.2 26.133333333333,51.35 26.333333333333,51.683333333333 26.133333333333,51.583333333333 25.916666666667,51.2 26.133333333333</POLYGON></GEOMETRY></ASP><ASP CATEGORY="RESTRICTED"><VERSION>1708909912012</VERSION><ID>62614fefcb27f42509460954</ID><COUNTRY>QA</COUNTRY><NAME>OT-R54</NAME><ALTLIMIT_TOP REFERENCE="MSL"><ALT UNIT="F">1500</ALT></ALTLIMIT_TOP><ALTLIMIT_BOTTOM REFERENCE="GND"><ALT UNIT="F">0</ALT></ALTLIMIT_BOTTOM><GEOMETRY><POLYGON>51.494444444444 24.9,51.494444444444 24.861111111111,51.455555555556 24.861111111111,51.455555555556 24.9,51.494444444444 24.9</POLYGON></GEOMETRY></ASP><ASP CATEGORY="RESTRICTED"><VERSION>1708909912012</VERSION><ID>62614fefcb27f42509460961</ID><COUNTRY>QA</COUNTRY><NAME>OT-R55 RAS LAFFAN</NAME><ALTLIMIT_TOP REFERENCE="MSL"><ALT UNIT="F">3000</ALT></ALTLIMIT_TOP><ALTLIMIT_BOTTOM REFERENCE="GND"><ALT UNIT="F">0</ALT></ALTLIMIT_BOTTOM><GEOMETRY><POLYGON>51.344444444444 26.141899440905,51.351854154689 26.141566351575,51.359189688471 26.140570418066,51.366377615661 26.138921610268,51.373345991129 26.136636433172,51.380025078182 26.133737760833,51.386348049346 26.130254606307,51.392251657359 26.126221829923,51.397676869516 26.121679788873,51.402569458961 26.116673931706,51.406880546947 26.11125434187,51.41056709064 26.105475234943,51.413592311624 26.099394414682,51.415926060884 26.093072693398,51.417545116727 26.086573282537,51.418433412802 26.079961159618,51.418582194105 26.073302417916,51.417990099583 26.066663605409,51.416663170722 26.060111059643,51.414614786213 26.053710245135,51.411865523575 26.047525099941,51.408442949268 26.041617397884,51.404381339596 26.036046132754,51.399721335301 26.030866930588,51.394509533442 26.026131495823,51.388798020682 26.021887096771,51.382643852718 26.018176095476,51.376108485032 26.015035526566,51.369257160632 26.012496729205,51.362158260808 26.010585035766,51.354882625296 26.009319520239,51.347502848489 26.008712808843,51.340092558584 26.008770954675,51.332725686657 26.009493377624,51.325475732802 26.010872870129,51.318415036461 26.012895668728,51.311614058042 26.015541590698,51.305140678827 26.018784234464,51.299059526008 26.022591241818,51.293431329453 26.02692461939,51.288312316536 26.031741116245,51.283753650995 26.036992653905,51.279800921409 26.042626804589,51.276493684399 26.048587312982,51.273865067174 26.054814656404,51.271941433476 26.061246637867,51.270742116374 26.06781900615,51.270279220733 26.074466096776,51.270557497493 26.081121487519,51.27157429122 26.087718661912,51.273319561629 26.094191674161,51.27577597908 26.100475808791,51.278919093282 26.106508228418,51.282717573701 26.112228603138,51.287133519416 26.117579715171,51.292122835478 26.122508032677,51.297635672096 26.126964246892,51.303616922316 26.130903767167,51.310006773261 26.134287168848,51.316741305381 26.137080589436,51.323753133682 26.139256068993,51.330972084421 26.140791831291,51.338325900371 26.141672502843,51.344444444444 26.141899440905</POLYGON></GEOMETRY></ASP><ASP CATEGORY="RESTRICTED"><VERSION>1708909912012</VERSION><ID>62614fefcb27f4250946096e</ID><COUNTRY>QA</COUNTRY><NAME>OT-R56</NAME><ALTLIMIT_TOP REFERENCE="MSL"><ALT UNIT="F">5000</ALT></ALTLIMIT_TOP><ALTLIMIT_BOTTOM REFERENCE="GND"><ALT UNIT="F">0</ALT></ALTLIMIT_BOTTOM><GEOMETRY><POLYGON>51.312777777778 25.201610412242,51.320999564218 25.201277243675,51.329155475333 25.200280407433,51.33718016683 25.198627890379,51.345009352104 25.196332932392,51.352580320149 25.19341391966,51.35983244049 25.189894236515,51.366707650955 25.185802077042,51.373150924311 25.181170218013,51.379110709958 25.176035755017,51.384539347074 25.170439803936,51.389393445904 25.164427170249,51.393634234129 25.15804598883,51.397227865552 25.151347337218,51.400145688702 25.144384825487,51.402364473251 25.137214166062,51.40386659254 25.129892726962,51.404640160836 25.122479072087,51.404679124372 25.115032492259,51.403983305537 25.107612530782,51.402558400024 25.100278507324,51.400415927082 25.093089043937,51.3975731334 25.086101596987,51.39405285154 25.079371998714,51.389883314136 25.072954012058,51.385097925473 25.066898902273,51.379734992343 25.061255028695,51.373837416393 25.056067459895,51.36745235048 25.051377615213,51.360630821777 25.04722293549,51.353427324662 25.043636585578,51.345899386597 25.040647190929,51.338107110423 25.038278610326,51.330112696668 25.036549746516,51.321979949573 25.035474396225,51.313773770703 25.0350611407,51.305559644059 25.035313277641,51.297403116674 25.036228795048,51.289369278737 25.037800387175,51.281522247234 25.040015512484,51.273924657141 25.042856493131,51.266637164083 25.046300655236,51.259717962355 25.050320508828,51.253222322029 25.054883966079,51.24720214881 25.059954596138,51.241705570069 25.065491914568,51.236776550346 25.07145170514,51.232454539383 25.077786371472,51.228774155515 25.084445315756,51.225764906979 25.091375341611,51.223450953435 25.098521077887,51.22185090969 25.105825420097,51.220977693275 25.113229985963,51.220838417227 25.120675581496,51.221434329043 25.128102673894,51.222760796435 25.135451867481,51.224807340128 25.14266437891,51.227557713592 25.149682507797,51.230990029169 25.156450099015,51.235076929751 25.16291299293,51.239785804699 25.169019459923,51.245079048406 25.174720615689,51.250914359481 25.179970813941,51.25724507823 25.18472801331,51.264020559749 25.188954115452,51.271186579648 25.192615271601,51.278685769152 25.195682155046,51.286458076028 25.198130197296,51.294441247605 25.199939785998,51.302571331912 25.201096422973,51.310783192845 25.201590841063,51.312777777778 25.201610412242</POLYGON></GEOMETRY></ASP><ASP CATEGORY="RESTRICTED"><VERSION>1708909912012</VERSION><ID>62614fefcb27f4250946097a</ID><COUNTRY>QA</COUNTRY><NAME>OT-R58</NAME><ALTLIMIT_TOP REFERENCE="MSL"><ALT UNIT="F">3000</ALT></ALTLIMIT_TOP><ALTLIMIT_BOTTOM REFERENCE="GND"><ALT UNIT="F">0</ALT></ALTLIMIT_BOTTOM><GEOMETRY><POLYGON>51.408333333333 25.224983123673,51.412824314218 25.224650502723,51.417195663174 25.223661500355,51.42133094077 25.222042461562,51.425120006773 25.219836512835,51.428461957609 25.217102411488,51.43126781584 25.213912978229,51.4334628997 25.210353155028,51.434988809548 25.206517740369,51.435804978524 25.202508862533,51.435889746568 25.198433258498,51.435240929848 25.194399431122,51.433875871181 25.190514760431,51.431830970947 25.186882645926,51.429160711743 25.18359975588,51.425936203423 25.18075345663,51.42224328771 25.178419490031,51.418180253112 25.176659960512,51.413855220916 25.175521684997,51.409383271595 25.175034949237,51.404883387608 25.175212703407,51.400475293301 25.176050218167,51.396276275239 25.177525210264,51.392398066828 25.179598434365,51.388943879407 25.182214725501,51.386005658254 25.18530446464,51.383661636167 25.188785428665,51.381974249595 25.192564975892,51.380988472924 25.196542509297,51.380730615624 25.200612152206,51.381207614868 25.204665565472,51.382406843188 25.208594831296,51.384296437101 25.212295326973,51.38682613875 25.215668511962,51.389928628862 25.218624553913,51.393521316073 25.221084723449,51.397508535278 25.222983493607,51.401784096539 25.224270287678,51.406234116467 25.224910828555,51.408333333333 25.224983123673</POLYGON></GEOMETRY></ASP><ASP CATEGORY="RESTRICTED"><VERSION>1708909912012</VERSION><ID>62614fefcb27f42509460987</ID><COUNTRY>QA</COUNTRY><NAME>OT-R59 UMM SAID FERTILIZER PLANT</NAME><ALTLIMIT_TOP REFERENCE="MSL"><ALT UNIT="F">3000</ALT></ALTLIMIT_TOP><ALTLIMIT_BOTTOM REFERENCE="GND"><ALT UNIT="F">0</ALT></ALTLIMIT_BOTTOM><GEOMETRY><POLYGON>51.566666666667 24.949966247345,51.573016861601 24.9496332822,51.579282356035 24.948638827959,51.585379583289 24.946996148754,51.591227228928 24.944727154107,51.596747318623 24.941862105691,51.601866260699 24.938439212384,51.60651582929 24.934504119114,51.610634074864 24.930109296398,51.614166149879 24.925313338853,51.617065038583 24.920180182154,51.619292181261 24.914778248985,51.62081798474 24.909179535505,51.621622212514 24.90345865058,51.621694249518 24.897691820695,51.621033238278 24.891955873833,51.61964808491 24.886327215908,51.617557335156 24.880880813392,51.614788922423 24.875689195644,51.611379791411 24.870821490195,51.607375402578 24.866342503748,51.602829124229 24.862311861035,51.597801520428 24.858783212885,51.592359544295 24.855803523934,51.586575647413 24.853412449325,51.580526817142 24.851641808575,51.574293554534 24.850515163525,51.567958806262 24.85004750587,51.561606864587 24.850245058373,51.55532224972 24.851105192362,51.549188589224 24.852616462582,51.543287509062 24.854758758947,51.53769755083 24.857503573216,51.532493129324 24.860814377097,51.527743544136 24.864647106832,51.523512058284 24.868950747919,51.519855056057 24.873668012306,51.516821291252 24.87873609915,51.514451235854 24.884087529154,51.512776537923 24.889651041473,51.511819596082 24.89535254136,51.511593256451 24.901116086016,51.512100636338 24.906864895573,51.513335077296 24.912522375792,51.515280228465 24.918013138849,51.517910259357 24.923264008598,51.521190199554 24.928204996871,51.525076400985 24.932770237728,51.529517116856 24.936898867112,51.534453189629 24.940535836088,51.539818838985 24.94363264668,51.545542539259 24.946148000394,51.551547974622 24.94804835065,51.557755059149 24.949308351638,51.564081008005 24.949911197522,51.566666666667 24.949966247345</POLYGON></GEOMETRY></ASP><ASP CATEGORY="RESTRICTED"><VERSION>1708909912012</VERSION><ID>62614fefcb27f42509460994</ID><COUNTRY>QA</COUNTRY><NAME>OT-R60</NAME><ALTLIMIT_TOP REFERENCE="MSL"><ALT UNIT="F">1000</ALT></ALTLIMIT_TOP><ALTLIMIT_BOTTOM REFERENCE="GND"><ALT UNIT="F">0</ALT></ALTLIMIT_BOTTOM><GEOMETRY><POLYGON>51.381388888889 25.769219184483,51.382380955257 25.769129541274,51.383333466722 25.768864185834,51.384208445997 25.768433698177,51.384971008024 25.767855242166,51.385590751106 25.767151880986,51.386042969053 25.766351657373,51.386309635971 25.765486475331,51.386380124494 25.764590827967,51.386251628858 25.763700422198,51.385929276064 25.762850755179,51.38542592081 25.762075699232,51.384761632453 25.761406151652,51.383962894571 25.760868803203,51.383061549064 25.760485074357,51.382093526919 25.76027026163,51.381097416198 25.760232928,51.380112924272 25.760374561674,51.379179295515 25.760689516788,51.378333747417 25.761165238386,51.377609987365 25.761782762744,51.37703686915 25.762517473109,51.37663724269 25.763340080774,51.37642704284 25.764217792435,51.376414653645 25.765115617322,51.376600573455 25.765997762039,51.376977394363 25.766829057528,51.377530096876 25.767576361265,51.378236648199 25.768209878763,51.379068880341 25.768704351684,51.379993613089 25.769040065115,51.380973977069 25.769203633836,51.381388888889 25.769219184483</POLYGON></GEOMETRY></ASP><ASP CATEGORY="RESTRICTED"><VERSION>1708909912012</VERSION><ID>62614fefcb27f425094609a1</ID><COUNTRY>QA</COUNTRY><NAME>OT-R61 UMM SAID MILITARY TRAINING AREA</NAME><ALTLIMIT_TOP REFERENCE="MSL"><ALT UNIT="F">3000</ALT></ALTLIMIT_TOP><ALTLIMIT_BOTTOM REFERENCE="GND"><ALT UNIT="F">0</ALT></ALTLIMIT_BOTTOM><GEOMETRY><POLYGON>51.5 25.033299580679,51.506354501498 25.032966615021,51.512624244665 25.03197215927,51.518725605787 25.03032947764,51.524577214972 25.028060479779,51.530101044769 25.025195427531,51.535223453443 25.021772529981,51.539876168813 25.017837432279,51.543997199391 25.013442605178,51.547531660607 25.00864664353,51.550432505098 25.003513483227,51.552661147362 24.998111547144,51.554187974594 24.992512831594,51.554992737057 24.986791945555,51.555064813008 24.98102511557,51.554403344913 24.975289169625,51.553017245421 24.969660513589,51.550925073296 24.964214113831,51.548154781253 24.959022499565,51.544743339311 24.954154798136,51.540736238912 24.949675816034,51.536186884577 24.945645177759,51.531155881339 24.942116533906,51.525710227489 24.939136848884,51.519922423393 24.936745777624,51.513869508164 24.934975139468,51.507632036899 24.93384849612,51.501293011921 24.933380839182,51.49493678201 24.933578391381,51.488647924052 24.934438524061,51.482510121697 24.935949792035,51.476605055694 24.938092085338,51.471011320407 24.940836895891,51.465803380698 24.944147695598,51.461050582874 24.947980420923,51.456816232699 24.952284057599,51.453156752672 24.957001317807,51.450120929755 24.962069400927,51.447749263599 24.967420827859,51.446073424056 24.972984337921,51.445115825352 24.978685836487,51.444889322795 24.984449380826,51.445397036322 24.990198191089,51.446632303497 24.995855673,51.448578762872 25.001346438644,51.45121056691 25.006597311739,51.454492721871 25.011538303938,51.458381550395 25.016103549091,51.462825270804 25.020232182917,51.467764685548 25.023869156242,51.47313396969 25.026965970858,51.478861548947 25.02948132806,51.48487105553 25.03138168108,51.491082348914 25.032641683962,51.497412587778 25.033244530771,51.5 25.033299580679</POLYGON></GEOMETRY></ASP><ASP CATEGORY="RESTRICTED"><VERSION>1708909912012</VERSION><ID>62614fefcb27f425094609af</ID><COUNTRY>QA</COUNTRY><NAME>OT-R62 UMM AL-SHOKHOT</NAME><ALTLIMIT_TOP REFERENCE="MSL"><ALT UNIT="F">13000</ALT></ALTLIMIT_TOP><ALTLIMIT_BOTTOM REFERENCE="GND"><ALT UNIT="F">0</ALT></ALTLIMIT_BOTTOM><GEOMETRY><POLYGON>51.357777777778 25.751077358457,51.36417017856 25.750744388358,51.370477312116 25.749749919522,51.376615052825 25.748107216856,51.382501542773 25.745838191129,51.388058287045 25.742973105666,51.393211203379 25.739550171317,51.39789161198 25.735615035189,51.40203715215 25.731220170077,51.405592613453 25.726424172852,51.408510670298 25.721290981297,51.410752510228 25.715889019948,51.412288347651 25.710290286458,51.413097816346 25.704569390757,51.413170235759 25.6988025599,51.412504747793 25.693066621919,51.411110322572 25.687437982257,51.409005633405 25.681991606414,51.406218802899 25.676800022333,51.402787023888 25.671932355756,51.398756060445 25.667453411322,51.394179635822 25.663422811531,51.389118715593 25.659894204937,51.383640695601 25.656914553969,51.377818505529 25.654523511754,51.371729639961 25.652752896092,51.365455129682 25.651626267492,51.359078466758 25.651158616776,51.352684497441 25.65135616634,51.346358297396 25.652216287667,51.340184043927 25.653727536173,51.334243899938 25.655869802926,51.32861692421 25.658614581256,51.32337802225 25.661925344776,51.318596951481 25.665758031869,51.314337393856 25.670061630299,51.310656108145 25.674778854277,51.307602173159 25.679846905106,51.305216332021 25.685198305401,51.303530446316 25.690761795894,51.302567067556 25.696463283001,51.302339131882 25.7022268246,51.302849782322 25.707975640988,51.304092321276 25.713633137566,51.306050294135 25.71912392564,51.308697703241 25.724374827738,51.311999349606 25.729315853972,51.315911298086 25.733881136386,51.320381460016 25.738009808717,51.325350285688 25.741646819745,51.330751557528 25.744743669259,51.336513273409 25.747259056698,51.342558608275 25.749159433687,51.348806941146 25.750419452995,51.355174933613 25.751022307812,51.357777777778 25.751077358457</POLYGON></GEOMETRY></ASP><ASP CATEGORY="RESTRICTED"><VERSION>1708909912012</VERSION><ID>62614fefcb27f425094609bb</ID><COUNTRY>QA</COUNTRY><NAME>OT-R63 HALUL ISLAND</NAME><ALTLIMIT_TOP REFERENCE="MSL"><ALT UNIT="F">10000</ALT></ALTLIMIT_TOP><ALTLIMIT_BOTTOM REFERENCE="GND"><ALT UNIT="F">0</ALT></ALTLIMIT_BOTTOM><GEOMETRY><POLYGON>52.410833333333 25.757721523353,52.419093235736 25.757388349034,52.427286954007 25.75639149572,52.435348837647 25.75473895082,52.443214299013 25.752443955104,52.450820333761 25.749524895966,52.458106028221 25.746005159221,52.465013049529 25.74191294067,52.471486114496 25.737281018973,52.477473433398 25.73214649172,52.482927125065 25.726550476851,52.487803599937 25.720537781878,52.492063908009 25.714156543635,52.495674048907 25.707457841476,52.498605241652 25.700495287087,52.500834152041 25.693324594254,52.502343075902 25.686003132061,52.503120076863 25.678589465145,52.503159077673 25.671142884709,52.502459904456 25.663722934075,52.501028283697 25.656388932561,52.498875792125 25.649199501519,52.496019760017 25.642212096281,52.492483128846 25.635482547753,52.48829426452 25.629064617289,52.483486727808 25.623009568348,52.478099003887 25.617365758328,52.472174193226 25.61217825377,52.465759666323 25.607488471966,52.458906685087 25.603333851754,52.451669993865 25.599747556089,52.444107383382 25.596758208694,52.436279230995 25.594389666846,52.428248020888 25.592660832058,52.420077847942 25.591585500131,52.411833909128 25.591172251726,52.403581986383 25.591424384319,52.395387924949 25.592339886046,52.38731711124 25.593911451661,52.379433954241 25.596126540471,52.371801374477 25.598967475795,52.364480304502 25.602411585196,52.357529204785 25.606431380383,52.351003598776 25.610994775391,52.344955630777 25.616065341351,52.339433650109 25.62160259587,52.334481824843 25.627562324758,52.3301397882 25.6338969336,52.326442320433 25.640555826422,52.323419068785 25.647485808485,52.321094307829 25.654631510041,52.319486742173 25.661935827708,52.318609353215 25.669340379996,52.318469291293 25.676785973351,52.319067814217 25.684213075041,52.320400272812 25.691562289097,52.322456143728 25.698774831521,52.325219109393 25.705793000938,52.328667184604 25.712560640932,52.332772888875 25.71902359031,52.337503463269 25.725130117682,52.342821130069 25.730831336816,52.348683393302 25.7360815994,52.355043377746 25.740838862009,52.361850203752 25.745065024277,52.369049394866 25.748726235518,52.37658331499 25.751793167258,52.384391631514 25.754241249461,52.392411800663 25.756050868499,52.400579571067 25.75720752522,52.408829501432 25.757701951835,52.410833333333 25.757721523353</POLYGON></GEOMETRY></ASP></AIRSPACES>
</OPENAIP>